{
  "db_name": "PostgreSQL",
  "query": "\n            SELECT key_id, key, signature\n            FROM signed_pre_keys\n            WHERE did = $1\n            LIMIT 1\n            ",
  "describe": {
    "columns": [
      {
        "ordinal": 0,
        "name": "key_id",
        "type_info": "Int4"
      },
      {
        "ordinal": 1,
        "name": "key",
        "type_info": "Bytea"
      },
      {
        "ordinal": 2,
        "name": "signature",
        "type_info": "Bytea"
      }
    ],
    "parameters": {
      "Left": [
        "Uuid"
      ]
    },
    "nullable": [
      false,
      false,
      false
    ]
  },
  "hash": "343544839d46e644df37d38d6af2f6ae38d5d700147bead8baa1f345e3e3dea3"
}
